{
    "mongodb": {
        "endpoint": "mongodb://decompany:decompany1234@172.31.47.117:27017/alpha-decompany"
    },
    "s3Config":{
        "document": "alpha-ca-document.decompany.io",
        "thumbnail": "alpha-ca-thumbnail.decompany.io",
        "profile": "alpha-ca-profile.decompany.io"
    },
    "tables":{
        "DOCUMENT": "DOCUMENT",
        "DOCUMENT_POPULAR": "DOCUMENT-POPULAR",
        "DOCUMENT_FEATURED": "DOCUMENT-FEATURED",
        "TRACKING": "TRACKING",
        "TRACKING_USER": "TRACKING-USER",
        "VOTE": "VOTE",
        "USER": "USER",
        "SEO_FRIENDLY": "SEO-FRIENDLY",
        "TOP_TAG": "TOP-TAG",
        "STAT_PAGEVIEW_DAILY": "STAT-PAGEVIEW-DAILY",
        "STAT_PAGEVIEW_TOTALCOUNT_DAILY": "STAT-PAGEVIEW-TOTALCOUNT-DAILY"
    },
    "sqsConfig": {
        "region": "us-west-1",
        "queueUrls": {
            "CONVERT_IMAGE": "https://sqs.us-west-1.amazonaws.com/197966029048/DEV-CA-CONVERT-IMAGE",
            "PAGEVIEW_TO_ONCHAIN": "https://sqs.us-west-1.amazonaws.com/197966029048/DEV-CA-SC-VIEWCOUNT",
            "LATEST_VOTE_READ_FROM_ONCHAIN": "https://sqs.us-west-1.amazonaws.com/197966029048/DEV-CA-SC-LATEST-VOTE-READ_FROM_ONCHAIN",
            "LATEST_CREATOR_REWARD_FROM_ONCHAIN": "https://sqs.us-west-1.amazonaws.com/197966029048/DEV-CA-SC-LATEST-CREATOR-REWARD-READ-FROM-ONCHAIN"
        }
    },
    "applicationLogAppender": {
        "enable": true,
        "region": "us-west-1",
        "streamName": "TrackingDataStream"
    }
}